illistrations/AtoB.py
illistrations/accompanieing_animations.py
illistrations/bijection_full_all.py
illistrations/build_graph.py
illistrations/build_tree.py
illistrations/build_tree2.py
illistrations/cubic_forcing.py
illistrations/example.py
illistrations/horisontalsequence.py
illistrations/ligth_theme.py
illistrations/nippising24-sequences.py
illistrations/poster_figures.py
illistrations/preprint.py
illistrations/stdc_basic.py
manim_lamination_builder/__init__.py
manim_lamination_builder/__main__.py
manim_lamination_builder/animation.py
manim_lamination_builder/chord.py
manim_lamination_builder/constructions.py
manim_lamination_builder/custom_json.py
manim_lamination_builder/lamination.py
manim_lamination_builder/main.py
manim_lamination_builder/morph.py
manim_lamination_builder/new_generate.py
manim_lamination_builder/points.py
manim_lamination_builder/pull_back_tree.py
manim_lamination_builder/pull_backs.py
manim_lamination_builder/rabbit_psi_and_quotent.py
manim_lamination_builder/sibling_trees.py
manim_lamination_builder/visual_settings.py
quotient_pinching/cheating_quotent.py
quotient_pinching/julia_set_with_motion.py
quotient_pinching/ligth_theme.py
quotient_pinching/psi.py
quotient_pinching/psi_animation.py
quotient_pinching/quotent_with_rays.py
quotient_pinching/rays.py
tests/animation_test.py
tests/chords_test.py
tests/double_orbit_test.py
tests/fraction_simplify_test.py
tests/generational_fdl_graph_test.py
tests/morph_test.py
tests/new_generate_test.py
tests/points_test.py
tests/pull_back_tree_test.py
tests/pull_backs_test.py
tests/sibling_portraits_test.py
tests/tree_benchmark.py
manim_lamination_builder-1.0.0.dist-info/LICENSE
manim_lamination_builder-1.0.0.dist-info/METADATA
manim_lamination_builder-1.0.0.dist-info/WHEEL
manim_lamination_builder-1.0.0.dist-info/top_level.txt
manim_lamination_builder-1.0.0.dist-info/RECORD
