Metadata-Version: 2.1
Name: manim_lamination_builder
Version: 1.0.0
Summary: a replacement to lamination builder that uses manim instead of the browser
Author-email: Forrest Hilton <forrestmhilton@gmail.com>
License: GNU AFFERO GENERAL PUBLIC LICENSE
Project-URL: Homepage, https://github.com/ForrestHilton/manim-lamination-builder
Classifier: Programming Language :: Python :: 3
Classifier: License :: OSI Approved :: GNU Affero General Public License v3
Classifier: Operating System :: OS Independent
Requires-Python: >=3.7
License-File: LICENSE
Requires-Dist: manim
Requires-Dist: json5
Requires-Dist: pydantic
